[{"country_code": "SJ", "postal_code": "9170", "place_name": "Longyearbyen", "latitude": "78.2191", "longitude": "15.64"}, {"country_code": "SJ", "postal_code": "9171", "place_name": "Longyearbyen", "latitude": "78.2191", "longitude": "15.64"}, {"country_code": "SJ", "postal_code": "9173", "place_name": "Ny-\u00c5lesund", "latitude": "78.9237", "longitude": "11.925"}, {"country_code": "SJ", "postal_code": "9175", "place_name": "Sveagruva", "latitude": "77.9003", "longitude": "16.7201"}, {"country_code": "SJ", "postal_code": "9178", "place_name": "Barentsburg", "latitude": "78.8874", "longitude": "18.5995"}, {"country_code": "SJ", "postal_code": "9176", "place_name": "Bj\u00f8rn\u00f8ya", "latitude": "78.267", "longitude": "14.8301"}, {"country_code": "SJ", "postal_code": "9174", "place_name": "Hopen", "latitude": "78.267", "longitude": "14.8301"}, {"country_code": "SJ", "postal_code": "8099", "place_name": "Jan Mayen", "latitude": "70.9498", "longitude": "-8.638"}]